event_tools-0.0.2.dist-info/METADATA
event_tools-0.0.2.dist-info/WHEEL
event_tools-0.0.2.dist-info/license_files/LICENSE
event_tools/__init__.py
event_tools/_eventalign.py
event_tools/_events.py
event_tools/event_tools.cpython-39-x86_64-linux-gnu.so
event_tools-0.0.2.dist-info/RECORD
