Metadata-Version: 2.1
Name: event-tools
Version: 0.0.2
Requires-Dist: numpy>=1.22.4
License-File: LICENSE
Author: Jinyang Zhang <zhangjinyang@biols.ac.cn
Author-email: Jinyang Zhang <zhangjinyang@biols.ac.cn
Maintainer: Jinyang Zhang
Maintainer-email: zhangjinyang@biols.ac.cn
Requires-Python: >=3.7
Project-URL: homepage, https://github.com/Kevinzjy/event-tools
